aluControlUnit.v
//=========================================================================
// Name & Email must be EXACTLY as in Gradescope roster!
// Name:Garvin Ha 
// Email:gha003@ucr.edu
// 
// Assignment name: Lab2-DatapathControlUnits
// Lab section: 021
// TA: Eren, Omar
// 
// I hereby certify that I have not received assistance on this assignment,
// or used code, from ANY outside source other than the instruction team
// (apart from what was provided in the starter file).
//
//=========================================================================

module aluControlUnit (
    input  wire [1:0] alu_op, 
    input  wire [5:0] instruction_5_0, 
    output reg [3:0] alu_out
    );

// ------------------------------
// Insert your solution below
// ------------------------------ 

endmodule

controlUnit.v
//=========================================================================
// Name & Email must be EXACTLY as in Gradescope roster!
// Name: Garvin Ha 
// Email: gha003@ucr.edu
// 
// Assignment name: Lab2-DatapathControlUnits
// Lab section: 021
// TA: Eren, Omar
// 
// I hereby certify that I have not received assistance on this assignment,
// or used code, from ANY outside source other than the instruction team
// (apart from what was provided in the starter file).
//
//=========================================================================

module controlUnit  (
    input  wire [5:0] instr_op, 
    output wire       reg_dst,   
    output wire       branch,     
    output wire       mem_read,  
    output wire       mem_to_reg,
    output wire [1:0] alu_op,        
    output wire       mem_write, 
    output wire       alu_src,    
    output wire       reg_write
    );

// ------------------------------
// Insert your solution below

// ------------------------------ 

endmodule

datapath_tb.v
//=========================================================================
// Name & Email must be EXACTLY as in Gradescope roster!
// Name: Garvin Ha 
// Email: gha003@ucr.edu
// 
// Assignment name: Lab2-DatapathControlUnits
// Lab section: 021
// TA: Eren, Omar
// 
// I hereby certify that I have not received assistance on this assignment,
// or used code, from ANY outside source other than the instruction team
// (apart from what was provided in the starter file).
//
//=========================================================================

`timescale 1ns / 1ps

module datapath_tb;
    // Inputs
    reg clk; 
    reg [5:0] instr_op;    
    reg [5:0] instr_field;

    wire [8:0] result;
    wire [3:0] alu_result;

    reg [8:0] R;
    reg [3:0] R_alu;

    // -------------------------------------------------------
    // Setup output file for possible debugging uses
    // -------------------------------------------------------
    initial
    begin
        $dumpfile("lab04.vcd");
        $dumpvars(0);
    end
    
    // ---------------------------------------------------
    // Instantiate the Units Under Test (UUT)
    // --------------------------------------------------- 
    controlUnit uut1 (
        .instr_op(instr_op),
        .reg_dst(result[8]),
        .alu_src(result[7]),
        .mem_to_reg(result[6]),
        .reg_write(result[5]),
        .mem_read(result[4]),
        .mem_write(result[3]),
        .branch(result[2]),
        .alu_op(result[1:0])
    );

    aluControlUnit uut2 (
        .alu_op(result[1:0]),
        .instruction_5_0(instr_field),
        .alu_out(alu_result)
    );

    initial begin 
        clk = 0;
        forever begin 
            clk = ~clk; #10; 
        end 
    end
     
    integer failedTests = 0;
    integer totalTests = 0;
    initial begin
        // Reset
        @(posedge clk); // Wait for first clock out of reset 
        #10; // Wait 

        // -------------------------------------------------------
        // Test group 1: Control Unit
        // -------------------------------------------------------
        $display("Test Group 1: Testing Control unit... ");

        $write("\tTest Case 1.1: R-format ...");
        totalTests = totalTests + 1;
        // Set inputs
        instr_op = 6'b000000;
        R = { 9'b100100010 }; 
        #100; // Wait
        if (R != result) begin
            $display("failed: Expected: %b, got %b", R, result); 
            failedTests = failedTests + 1;
        end else begin
            $display("passed"); 
        end

        $write("\tTest Case 1.2: lw ...");
        totalTests = totalTests + 1;
        // Set inputs
        instr_op = 6'b100011;
        R = { 9'b011110000 }; 
        #100; // Wait
        if (R != result) begin
            $display("failed: Expected: %b, got %b", R, result); 
            failedTests = failedTests + 1;
        end else begin
            $display("passed"); 
        end

        $write("\tTest Case 1.3: sw ...");
        totalTests = totalTests + 1;
        // Set inputs
        instr_op = 6'b101011;
        R = { 9'b010001000 }; 
        #100; // Wait
        if (R != result) begin
            $display("failed: Expected: %b, got %b", R, result); 
            failedTests = failedTests + 1;
        end else begin
            $display("passed"); 
        end        

        $write("\tTest Case 1.4: beq ...");
        totalTests = totalTests + 1;
        // Set inputs
        instr_op = 6'b000100;
        R = { 9'b000000101 }; 
        #100; // Wait
        if (R != result) begin
            $display("failed: Expected: %b, got %b", R, result); 
            failedTests = failedTests + 1;
        end else begin
            $display("passed"); 
        end

        $write("\tTest Case 1.4: imm ...");
        totalTests = totalTests + 1;
        // Set inputs
        instr_op = 6'b001000;
        R = { 9'b100100010 }; 
        #100; // Wait
        if (R != result) begin
            $display("failed: Expected: %b, got %b", R, result); 
            failedTests = failedTests + 1;
        end else begin
            $display("passed"); 
        end
        // -------------------------------------------------------
        // More Control Unit tests jere
        // -------------------------------------------------------

        // -------------------------------------------------------
        // Test group 2: ALU Control Unit
        // -------------------------------------------------------
        $display("\nTest Group 2: Testing ALU Control unit... ");

        $write("\tTest Case 2.1: R-type (add) ...");
        totalTests = totalTests + 1;
        // Set inputs
        instr_op = 6'b000000;
        instr_field = 6'b100000;
        R_alu = { 4'b0010 }; 
        #100; // Wait
        if (R_alu !== alu_result) begin
            $display("failed: Expected: %b, got %b", R_alu, alu_result); 
            failedTests = failedTests + 1;
        end else begin
            $display("passed"); 
        end

        $write("\tTest Case 2.2: R-type (subtract) ...");
        totalTests = totalTests + 1;
        // Set inputs
        instr_op = 6'b000000;
        instr_field = 6'b100010;
        R_alu = { 4'b0110 }; 
        #100; // Wait
        if (R_alu !== alu_result) begin
            $display("failed: Expected: %b, got %b", R_alu, alu_result); 
            failedTests = failedTests + 1;
        end else begin
            $display("passed"); 
        end

        $write("\tTest Case 2.3: R-type (AND) ...");
        totalTests = totalTests + 1;
        // Set inputs
        instr_op = 6'b000000;
        instr_field = 6'b100100;
        R_alu = { 4'b0000 }; 
        #100; // Wait
        if (R_alu !== alu_result) begin
            $display("failed: Expected: %b, got %b", R_alu, alu_result); 
            failedTests = failedTests + 1;
        end else begin
            $display("passed"); 
        end

        $write("\tTest Case 2.4: R-type (OR) ...");
        totalTests = totalTests + 1;
        // Set inputs
        instr_op = 6'b000000;
        instr_field = 6'b100101;
        R_alu = { 4'b0001 }; 
        #100; // Wait
        if (R_alu !== alu_result) begin
            $display("failed: Expected: %b, got %b", R_alu, alu_result); 
            failedTests = failedTests + 1;
        end else begin
            $display("passed"); 
        end

        $write("\tTest Case 2.5: R-type (NOR) ...");
        totalTests = totalTests + 1;
        // Set inputs
        instr_op = 6'b000000;
        instr_field = 6'b100111;
        R_alu = { 4'b1100 }; 
        #100; // Wait
        if (R_alu !== alu_result) begin
            $display("failed: Expected: %b, got %b", R_alu, alu_result); 
            failedTests = failedTests + 1;
        end else begin
            $display("passed"); 
        end

        $write("\tTest Case 2.6: R-type (Set on less than) ...");
        totalTests = totalTests + 1;
        // Set inputs
        instr_op = 6'b000000;
        instr_field = 6'b101010;
        R_alu = { 4'b0111 }; 
        #100; // Wait
        if (R_alu !== alu_result) begin
            $display("failed: Expected: %b, got %b", R_alu, alu_result); 
            failedTests = failedTests + 1;
        end else begin
            $display("passed"); 
        end

        $write("\tTest Case 2.7: lw ...");
        totalTests = totalTests + 1;
        // Set inputs
        instr_op = 6'b000000;
        instr_field = 6'b000000;
        R_alu = { 4'b0010 }; 
        #100; // Wait
        if (R_alu !== alu_result) begin
            $display("failed: Expected: %b, got %b", R_alu, alu_result); 
            failedTests = failedTests + 1;
        end else begin
            $display("passed"); 
        end

        $write("\tTest Case 2.8: sw ...");
        totalTests = totalTests + 1;
        // Set inputs
        instr_op = 6'b000000;
        instr_field = 6'b000000;
        R_alu = { 4'b0010 }; 
        #100; // Wait
        if (R_alu !== alu_result) begin
            $display("failed: Expected: %b, got %b", R_alu, alu_result); 
            failedTests = failedTests + 1;
        end else begin
            $display("passed"); 
        end

        $write("\tTest Case 2.9: beq ...");
        totalTests = totalTests + 1;
        // Set inputs
        instr_op = 6'b000000;
        instr_field = 6'b000000;
        R_alu = { 4'b0110 }; 
        #100; // Wait
        if (R_alu !== alu_result) begin
            $display("failed: Expected: %b, got %b", R_alu, alu_result); 
            failedTests = failedTests + 1;
        end else begin
            $display("passed"); 
        end
        // -------------------------------------------------------
        // More ALU Control Unit tests jere
        // -------------------------------------------------------

        // --------------------------------------------------------------
        // End testing
        // --------------------------------------------------------------
        $write("\n--------------------------------------------------------------");
        $write("\nTesting complete\nPassed %0d / %0d tests",totalTests-failedTests,totalTests);
        $write("\n--------------------------------------------------------------\n");
        $finish();
    end
endmodule

lab04.vcd
$date
	Sat Apr 22 00:01:52 2023
$end
$version
	Icarus Verilog
$end
$timescale
	1ps
$end
$scope module datapath_tb $end
$var wire 9 ! result [8:0] $end
$var wire 4 " alu_result [3:0] $end
$var reg 9 # R [8:0] $end
$var reg 4 $ R_alu [3:0] $end
$var reg 1 % clk $end
$var reg 6 & instr_field [5:0] $end
$var reg 6 ' instr_op [5:0] $end
$var integer 32 ( failedTests [31:0] $end
$var integer 32 ) totalTests [31:0] $end
$scope module uut1 $end
$var wire 2 * alu_op [1:0] $end
$var wire 1 + alu_src $end
$var wire 1 , branch $end
$var wire 6 - instr_op [5:0] $end
$var wire 1 . mem_read $end
$var wire 1 / mem_to_reg $end
$var wire 1 0 mem_write $end
$var wire 1 1 reg_dst $end
$var wire 1 2 reg_write $end
$upscope $end
$scope module uut2 $end
$var wire 2 3 alu_op [1:0] $end
$var wire 6 4 instruction_5_0 [5:0] $end
$var reg 4 5 alu_out [3:0] $end
$upscope $end
$upscope $end
$enddefinitions $end
#0
$dumpvars
bx 5
bx 4
bz 3
z2
z1
z0
z/
z.
bx -
z,
z+
bz *
b0 )
b0 (
bx '
bx &
1%
bx $
bx #
bx "
bz !
$end
#10000
0%
#20000
1%
#30000
b100100010 #
b0 '
b0 -
b1 )
0%
#40000
1%
#50000
0%
#60000
1%
#70000
0%
#80000
1%
#90000
0%
#100000
1%
#110000
0%
#120000
1%
#130000
0%
b11110000 #
b100011 '
b100011 -
b10 )
#140000
1%
#150000
0%
#160000
1%
#170000
0%
#180000
1%
#190000
0%
#200000
1%
#210000
0%
#220000
1%
#230000
0%
b10001000 #
b101011 '
b101011 -
b11 )
#240000
1%
#250000
0%
#260000
1%
#270000
0%
#280000
1%
#290000
0%
#300000
1%
#310000
0%
#320000
1%
#330000
0%
b101 #
b100 '
b100 -
b100 )
#340000
1%
#350000
0%
#360000
1%
#370000
0%
#380000
1%
#390000
0%
#400000
1%
#410000
0%
#420000
1%
#430000
0%
b100100010 #
b1000 '
b1000 -
b101 )
#440000
1%
#450000
0%
#460000
1%
#470000
0%
#480000
1%
#490000
0%
#500000
1%
#510000
0%
#520000
1%
#530000
0%
b10 $
b100000 &
b100000 4
b0 '
b0 -
b110 )
#540000
1%
#550000
0%
#560000
1%
#570000
0%
#580000
1%
#590000
0%
#600000
1%
#610000
0%
#620000
1%
#630000
0%
b110 $
b100010 &
b100010 4
b111 )
b1 (
#640000
1%
#650000
0%
#660000
1%
#670000
0%
#680000
1%
#690000
0%
#700000
1%
#710000
0%
#720000
1%
#730000
0%
b0 $
b100100 &
b100100 4
b1000 )
b10 (
#740000
1%
#750000
0%
#760000
1%
#770000
0%
#780000
1%
#790000
0%
#800000
1%
#810000
0%
#820000
1%
#830000
0%
b1 $
b100101 &
b100101 4
b1001 )
b11 (
#840000
1%
#850000
0%
#860000
1%
#870000
0%
#880000
1%
#890000
0%
#900000
1%
#910000
0%
#920000
1%
#930000
0%
b1100 $
b100111 &
b100111 4
b1010 )
b100 (
#940000
1%
#950000
0%
#960000
1%
#970000
0%
#980000
1%
#990000
0%
#1000000
1%
#1010000
0%
#1020000
1%
#1030000
0%
b111 $
b101010 &
b101010 4
b1011 )
b101 (
#1040000
1%
#1050000
0%
#1060000
1%
#1070000
0%
#1080000
1%
#1090000
0%
#1100000
1%
#1110000
0%
#1120000
1%
#1130000
0%
b10 $
b0 &
b0 4
b1100 )
b110 (
#1140000
1%
#1150000
0%
#1160000
1%
#1170000
0%
#1180000
1%
#1190000
0%
#1200000
1%
#1210000
0%
#1220000
1%
#1230000
0%
b1101 )
b111 (
#1240000
1%
#1250000
0%
#1260000
1%
#1270000
0%
#1280000
1%
#1290000
0%
#1300000
1%
#1310000
0%
#1320000
1%
#1330000
0%
b110 $
b1110 )
b1000 (
#1340000
1%
#1350000
0%
#1360000
1%
#1370000
0%
#1380000
1%
#1390000
0%
#1400000
1%
#1410000
0%
#1420000
1%
#1430000
0%
b1001 (
